{
    "resLevelNr": 3,
    "resLevelBackgroundName": "level3",
    "resWaves": [
        {
            "resEnemiesInWave": [
                {
                    "resAirplanePos": [
                        0,
                        100
                    ],
                    "resAirplaneType": "Kamikaze"
                }
            ],
            "resWaveTimer": 50
        },
        {
            "resEnemiesInWave": [
                {
                    "resAirplanePos": [
                        -0,
                        -100
                    ],
                    "resAirplaneType": "Kamikaze"
                }
            ],
            "resWaveTimer": 50
        },
        {
            "resEnemiesInWave": [
                {
                    "resAirplanePos": [
                        -0,
                        -100
                    ],
                    "resAirplaneType": "Kamikaze"
                }
            ],
            "resWaveTimer": 50
        }
    ]
}